ignorance/__init__.py
ignorance-0.0.1.dist-info/LICENSE
ignorance-0.0.1.dist-info/METADATA
ignorance-0.0.1.dist-info/WHEEL
ignorance-0.0.1.dist-info/top_level.txt
ignorance-0.0.1.dist-info/RECORD
