Metadata-Version: 2.1
Name: ignorance
Version: 0.0.1
Summary: Ignorance is a lack of knowledge or information.
Author-email: Alexander Fedotov <alex.fedotov@aol.com>
Project-URL: Homepage, https://github.com/multilogue/ignorance
Project-URL: Bug Tracker, https://github.com/multilogue/ignorance/issues
Classifier: Programming Language :: Python :: 3
Classifier: License :: OSI Approved :: MIT License
Classifier: Operating System :: OS Independent
Requires-Python: >=3.10
License-File: LICENSE
